anova_wifi/__init__.py
anova_wifi/exceptions.py
anova_wifi/mocks/__init__.py
anova_wifi/mocks/anova_api.py
anova_wifi/parser.py
anova_wifi/py.typed
anova_wifi/web_socket_containers.py
anova_wifi/websocket_handler.py
anova_wifi-0.17.1.dist-info/LICENSE
anova_wifi-0.17.1.dist-info/METADATA
anova_wifi-0.17.1.dist-info/WHEEL
anova_wifi-0.17.1.dist-info/RECORD
