Metadata-Version: 2.1
Name: anova-wifi
Version: 0.17.1
Summary: A package to get read only data from Anova precision cookers with wifi
Home-page: https://github.com/Lash-L/anova_wifi
License: MIT
Author: Luke
Author-email: conway220@gmail.com
Requires-Python: >=3.10,<4.0
Classifier: Development Status :: 5 - Production/Stable
Classifier: Intended Audience :: Developers
Classifier: License :: OSI Approved :: MIT License
Classifier: Natural Language :: English
Classifier: Operating System :: OS Independent
Classifier: Programming Language :: Python :: 3
Classifier: Programming Language :: Python :: 3.10
Classifier: Programming Language :: Python :: 3.11
Classifier: Programming Language :: Python :: 3.12
Classifier: Topic :: Software Development :: Libraries
Requires-Dist: aiohttp (>=3.9.3,<4.0.0)
Project-URL: Bug Tracker, https://github.com/Lash-L/anova_wifi/issues
Project-URL: Changelog, https://github.com/Lash-L/anova_wifi/blob/main/CHANGELOG.md
Project-URL: Repository, https://github.com/Lash-L/anova_wifi
